extremeflash/__init__.py
extremeflash/__main__.py
extremeflash/tftp_server.py
extremeflash/ws_ap3710i.py
extremeflash/ws_ap3715i.py
extremeflash/ws_ap3825i.py
extremeflash/ws_ap3935i.py
extremeflash-0.5.0.dist-info/LICENSE
extremeflash-0.5.0.dist-info/METADATA
extremeflash-0.5.0.dist-info/WHEEL
extremeflash-0.5.0.dist-info/entry_points.txt
extremeflash-0.5.0.dist-info/RECORD
