Metadata-Version: 2.3
Name: extremeflash
Version: 0.5.0
Summary: 
License: GPL-3.0-only
Author: Grische
Author-email: 2787581+grische@users.noreply.github.com
Requires-Python: >=3.10,<4.0
Classifier: License :: OSI Approved :: GNU General Public License v3 (GPLv3)
Classifier: Programming Language :: Python :: 3
Classifier: Programming Language :: Python :: 3.10
Classifier: Programming Language :: Python :: 3.11
Classifier: Programming Language :: Python :: 3.12
Classifier: Programming Language :: Python :: 3.13
Requires-Dist: paramiko (>=3.0.0,<4.0.0)
Requires-Dist: pyserial (>=3.5,<4.0)
Requires-Dist: scp (>=0.14.5,<0.16.0)
Requires-Dist: tftpy (>=0.8.2,<0.9.0)
